beadsflow/__init__.py
beadsflow/__main__.py
beadsflow/application/__init__.py
beadsflow/application/errors.py
beadsflow/application/phase.py
beadsflow/application/run_epic.py
beadsflow/application/runner.py
beadsflow/application/select.py
beadsflow/application/session.py
beadsflow/domain/__init__.py
beadsflow/domain/models.py
beadsflow/entrypoints/__init__.py
beadsflow/entrypoints/cli.py
beadsflow/infra/__init__.py
beadsflow/infra/beads_cli.py
beadsflow/infra/locking.py
beadsflow/infra/paths.py
beadsflow/infra/run_command.py
beadsflow/infra/zellij.py
beadsflow/settings.py
beadsflow-0.1.0.dist-info/WHEEL
beadsflow-0.1.0.dist-info/entry_points.txt
beadsflow-0.1.0.dist-info/METADATA
beadsflow-0.1.0.dist-info/RECORD
