Metadata-Version: 2.3
Name: beadsflow
Version: 0.1.0
Summary: Standalone automation loop for repo-local Beads workflows
Requires-Python: >=3.11
